tikon/__init__.py
tikon/calibrador/__init__.py
tikon/calibrador/calib.py
tikon/calibrador/spotpy_.py
tikon/central/__init__.py
tikon/central/calibs.py
tikon/central/control.py
tikon/central/coso.py
tikon/central/datos.py
tikon/central/errores.py
tikon/central/exper.py
tikon/central/modelo.py
tikon/central/módulo.py
tikon/central/parc.py
tikon/central/paráms_exper.py
tikon/central/res.py
tikon/central/simul.py
tikon/central/tiempo.py
tikon/central/utils.py
tikon/config.py
tikon/consts.py
tikon/datos/__init__.py
tikon/datos/datos.py
tikon/datos/dibs.py
tikon/datos/obs.py
tikon/datos/proc.py
tikon/datos/valid.py
tikon/ecs/__init__.py
tikon/ecs/aprioris.py
tikon/ecs/dists/__init__.py
tikon/ecs/dists/anlt.py
tikon/ecs/dists/dibs.py
tikon/ecs/dists/dists.py
tikon/ecs/dists/trz.py
tikon/ecs/dists/utils.py
tikon/ecs/paráms.py
tikon/ecs/utils.py
tikon/ecs/árb_coso.py
tikon/ecs/árb_mód.py
tikon/ejemplos/__init__.py
"tikon/ejemplos/calibs/Opisina arenosella, Perera et al. 1988/Sitio A.json"
"tikon/ejemplos/calibs/Opisina arenosella, Perera et al. 1988/info.json"
"tikon/ejemplos/calibs/Opisina arenosella, Perera et al. 1988/red/O. arenosella.json"
"tikon/ejemplos/calibs/Opisina arenosella, Perera et al. 1988/red/Parasitoide larvas.json"
"tikon/ejemplos/calibs/Opisina arenosella, Perera et al. 1988/red/Parasitoide pupa.json"
tikon/ejemplos/calibs/__init__.py
tikon/ejemplos/datos/Perera et al 1988/Oarenosella_A.csv
tikon/ejemplos/datos/Perera et al 1988/Oarenosella_A.info.json
tikon/ejemplos/datos/Perera et al 1988/Oarenosella_B.csv
tikon/ejemplos/datos/Perera et al 1988/Oarenosella_B.info.json
tikon/ejemplos/datos/Perera et al 1988/__init__.py
tikon/ejemplos/datos/Perera et al 1988/ref.txt
tikon/ejemplos/datos/__init__.py
tikon/ejemplos/proyectos/__init__.py
tikon/ejemplos/proyectos/leucoptera_coffeella/Finca_El_Encanto.csv
tikon/ejemplos/proyectos/leucoptera_coffeella/L_coffeella.py
tikon/ejemplos/proyectos/leucoptera_coffeella/Suconusco_Chiapas.csv
tikon-3.0.0.dist-info/WHEEL
tikon-3.0.0.dist-info/METADATA
tikon-3.0.0.dist-info/RECORD
